printvarcolor/__init__.py
printvarcolor/helper.py
printvarcolor-1.0.0.dist-info/METADATA
printvarcolor-1.0.0.dist-info/WHEEL
printvarcolor-1.0.0.dist-info/top_level.txt
printvarcolor-1.0.0.dist-info/RECORD
